s3_credentials/__init__.py
s3_credentials/cli.py
s3_credentials/localserver.py
s3_credentials/policies.py
s3_credentials-0.17.dist-info/licenses/LICENSE
s3_credentials-0.17.dist-info/METADATA
s3_credentials-0.17.dist-info/WHEEL
s3_credentials-0.17.dist-info/entry_points.txt
s3_credentials-0.17.dist-info/top_level.txt
s3_credentials-0.17.dist-info/RECORD
