Metadata-Version: 2.4
Name: s3-credentials
Version: 0.17
Summary: A tool for creating credentials for accessing S3 buckets
Author: Simon Willison
License: Apache-2.0
Project-URL: Homepage, https://github.com/simonw/s3-credentials
Project-URL: Issues, https://github.com/simonw/s3-credentials/issues
Project-URL: CI, https://github.com/simonw/s3-credentials/actions
Project-URL: Changelog, https://github.com/simonw/s3-credentials/releases
Requires-Python: >=3.10
License-File: LICENSE
Requires-Dist: click
Requires-Dist: boto3
Dynamic: license-file
